starhopper/__init__.py
starhopper/formats/__init__.py
starhopper/formats/archive.py
starhopper/formats/btdx/__init__.py
starhopper/formats/btdx/file.py
starhopper/formats/cdb.py
starhopper/formats/common.py
starhopper/formats/esm/__init__.py
starhopper/formats/esm/file.py
starhopper/formats/esm/records/__init__.py
starhopper/formats/esm/records/base.py
starhopper/formats/esm/records/data.py
starhopper/formats/esm/records/edid.py
starhopper/formats/esm/records/fltv.py
starhopper/formats/esm/records/glob.py
starhopper/formats/esm/records/gmst.py
starhopper/formats/esm/records/types.py
starhopper/formats/mesh.py
starhopper/formats/strings.py
starhopper/gui/__init__.py
starhopper/gui/app.py
starhopper/gui/common.py
starhopper/gui/navigation.py
starhopper/gui/search.py
starhopper/gui/settings.py
starhopper/gui/viewers/__init__.py
starhopper/gui/viewers/archive_viewer.py
starhopper/gui/viewers/binary_viewer.py
starhopper/gui/viewers/esm_viewer.py
starhopper/gui/viewers/group_viewer.py
starhopper/gui/viewers/model_viewer.py
starhopper/gui/viewers/record_viewer.py
starhopper/gui/viewers/search_viewer.py
starhopper/gui/viewers/string_viewer.py
starhopper/gui/viewers/viewer.py
starhopper/gui/widgets/__init__.py
starhopper/gui/widgets/spinner.py
starhopper/io.py
starhopper-0.3.0.dist-info/LICENSE
starhopper-0.3.0.dist-info/METADATA
starhopper-0.3.0.dist-info/WHEEL
starhopper-0.3.0.dist-info/RECORD
