Metadata-Version: 2.1
Name: starhopper
Version: 0.3.0
Summary: Python utilties for ESM files.
License: MIT
Author: Tyler Kennedy
Author-email: tk@tkte.ch
Requires-Python: >=3.11,<3.12
Classifier: License :: OSI Approved :: MIT License
Classifier: Programming Language :: Python :: 3
Classifier: Programming Language :: Python :: 3.11
Requires-Dist: lz4 (>=4.3.2,<5.0.0)
